uniswap_fetcher_rs-0.1.11.dist-info/METADATA
uniswap_fetcher_rs-0.1.11.dist-info/WHEEL
uniswap_fetcher_rs/__init__.py
uniswap_fetcher_rs/__init__.pyi
uniswap_fetcher_rs/py.typed
uniswap_fetcher_rs/uniswap_fetcher_rs.cpython-312-x86_64-linux-gnu.so
uniswap_fetcher_rs-0.1.11.dist-info/RECORD
