Metadata-Version: 2.3
Name: uniswap_fetcher_rs
Version: 0.1.11
Summary: A Rust-based library to fetch and decode Uniswap V3 pool events, designed to be used as a Python module.
Keywords: uniswap,ethereum,rust,python,pyo3
Home-Page: https://github.com/analyzify360/uniswap-fetcher-rs
Author: venus1004@proton.me
Author-email: venus1004@proton.me
License: MIT
Project-URL: Source Code, https://github.com/analyzify360/uniswap-fetcher-rs
